cmdgraph.py
cmdgraph-0.1.dist-info/DESCRIPTION.rst
cmdgraph-0.1.dist-info/METADATA
cmdgraph-0.1.dist-info/RECORD
cmdgraph-0.1.dist-info/WHEEL
cmdgraph-0.1.dist-info/metadata.json
cmdgraph-0.1.dist-info/top_level.txt
