Metadata-Version: 2.0
Name: cmdgraph
Version: 0.1
Summary: A small set of complimentary tools for exploratory computational research
Home-page: http://github.com/MasonMcGill/cmdgraph
Author: Mason McGill
Author-email: mmcgill@caltech.edu
License: MIT
Platform: any
